{"name":"Practice","slug":"Practice","count":2,"postlist":[{"title":"Blender渲染练习（一） GameBoy","uid":"b6e7b3aff5c5f79e50f4a7f3232e41fe","slug":"BlenderPractice0","date":"2022-03-24T13:50:36.000Z","updated":"2022-03-27T12:25:10.308Z","comments":true,"path":"api/articles/BlenderPractice0.json","keywords":null,"cover":"static/img/Gameboy.png","text":"计划是每两天做一个简单的Blender渲染练习。目前想尝试一些low poly的渲染作品。 使用软件：Blender/Cycles本作品仅作为练习记录 效果图 ","link":"","photos":[],"count_time":{"symbolsCount":80,"symbolsTime":"1 mins."},"categories":[],"tags":[{"name":"Practice","slug":"Practice","count":2,"path":"api/tags/Practice.json"}],"author":{"name":"Polaerocy","slug":"blog-author","avatar":"/static/img/Avatar.jpeg","link":"/","description":"A graphic designer who aims to design the whole stack","socials":{"github":"","twitter":"","stackoverflow":"","wechat":"","qq":"","weibo":"","zhihu":"","csdn":"","juejin":"","customs":{}}},"feature":true},{"title":"Blender渲染练习（二） MagicBook","uid":"73f6fe89eb2c14c455fd048fecc697d2","slug":"BlenderPractice1","date":"2022-03-27T12:25:36.000Z","updated":"2022-03-27T12:33:55.419Z","comments":true,"path":"api/articles/BlenderPractice1.json","keywords":null,"cover":"static/img/MagicBook.png","text":"目前在做low poly风格的渲染练习进度中 使用软件：Blender/Eevee本作品仅作为练习记录 效果图 ","link":"","photos":[],"count_time":{"symbolsCount":56,"symbolsTime":"1 mins."},"categories":[],"tags":[{"name":"Practice","slug":"Practice","count":2,"path":"api/tags/Practice.json"}],"author":{"name":"Polaerocy","slug":"blog-author","avatar":"/static/img/Avatar.jpeg","link":"/","description":"A graphic designer who aims to design the whole stack","socials":{"github":"","twitter":"","stackoverflow":"","wechat":"","qq":"","weibo":"","zhihu":"","csdn":"","juejin":"","customs":{}}},"feature":true}]}